arxivAssistant/__init__.py
arxivAssistant/app.py
arxivAssistant/article.py
arxivAssistant/feed.py
arxivAssistant/list.py
arxivAssistant/scripts/__init__.py
arxivAssistant/scripts/today.py
arxivAssistant-0.3.1.dist-info/METADATA
arxivAssistant-0.3.1.dist-info/WHEEL
arxivAssistant-0.3.1.dist-info/entry_points.txt
arxivAssistant-0.3.1.dist-info/top_level.txt
arxivAssistant-0.3.1.dist-info/RECORD
