Metadata-Version: 2.1
Name: arxivAssistant
Version: 0.3.1
Summary: Read daily arxiv feed with console
Home-page: https://github.com/renecotyfanboy/arxivAssistant
Author: Simon Dupourqué
Author-email: sdupourque@irap.omp.eu
License: MIT
Requires-Python: >=3.9
Requires-Dist: feedparser
Requires-Dist: rich
Requires-Dist: textual
